awd_cli/__init__.py
awd_cli/cli.py
awd_cli/config.py
awd_cli/factory.py
awd_cli/version.py
awd_cli/adapters/__init__.py
awd_cli/adapters/client/__init__.py
awd_cli/adapters/client/base.py
awd_cli/adapters/client/vscode.py
awd_cli/adapters/package_manager/__init__.py
awd_cli/adapters/package_manager/base.py
awd_cli/adapters/package_manager/default_manager.py
awd_cli/core/__init__.py
awd_cli/core/operations.py
awd_cli/core/script_runner.py
awd_cli/deps/__init__.py
awd_cli/deps/aggregator.py
awd_cli/deps/verifier.py
awd_cli/registry/__init__.py
awd_cli/registry/client.py
awd_cli/registry/integration.py
awd_cli/runtime/__init__.py
awd_cli/runtime/base.py
awd_cli/runtime/codex_runtime.py
awd_cli/runtime/factory.py
awd_cli/runtime/llm_runtime.py
awd_cli/runtime/manager.py
awd_cli/utils/__init__.py
awd_cli/utils/helpers.py
awd_cli/workflow/__init__.py
awd_cli/workflow/discovery.py
awd_cli/workflow/parser.py
awd_cli/workflow/runner.py
awd_cli-0.0.10.dist-info/licenses/AUTHORS
awd_cli-0.0.10.dist-info/licenses/LICENSE
awd_cli-0.0.10.dist-info/METADATA
awd_cli-0.0.10.dist-info/WHEEL
awd_cli-0.0.10.dist-info/entry_points.txt
awd_cli-0.0.10.dist-info/top_level.txt
awd_cli-0.0.10.dist-info/RECORD
