Metadata-Version: 2.4
Name: awd-cli
Version: 0.0.10
Summary: MCP configuration tool
Author-email: Daniel Meppiel <user@example.com>
License: MIT License
Classifier: Programming Language :: Python :: 3
Classifier: Programming Language :: Python :: 3.13
Classifier: License :: OSI Approved :: MIT License
Classifier: Operating System :: OS Independent
Requires-Python: >=3.8
License-File: LICENSE
License-File: AUTHORS
Requires-Dist: click>=8.0.0
Requires-Dist: colorama>=0.4.6
Requires-Dist: pyyaml>=6.0.0
Requires-Dist: requests>=2.28.0
Requires-Dist: python-frontmatter>=1.0.0
Requires-Dist: llm>=0.17.0
Requires-Dist: llm-github-models>=0.1.0
Requires-Dist: tomli>=1.2.0; python_version < "3.11"
Requires-Dist: rich>=13.0.0
Requires-Dist: rich-click>=1.7.0
Provides-Extra: dev
Requires-Dist: pytest>=7.0.0; extra == "dev"
Requires-Dist: pytest-cov>=4.0.0; extra == "dev"
Requires-Dist: black>=23.0.0; extra == "dev"
Requires-Dist: isort>=5.0.0; extra == "dev"
Requires-Dist: mypy>=1.0.0; extra == "dev"
Provides-Extra: build
Requires-Dist: pyinstaller>=6.0.0; extra == "build"
Dynamic: license-file
